lins_utils/__init__.py
lins_utils/encrypt.py
lins_utils-0.1.0.2.dist-info/METADATA
lins_utils-0.1.0.2.dist-info/WHEEL
lins_utils-0.1.0.2.dist-info/top_level.txt
lins_utils-0.1.0.2.dist-info/RECORD
