Metadata-Version: 2.1
Name: lins-utils
Version: 0.1.0.2
Summary: Pacote com funções uteis para diversos projetos
Home-page: https://bitbucket.org/grupolinsferrao/pypck-lins_utils/
Author: Halyson Sampaio
Author-email: halyson@lojaspompeia.com.br
License: MIT
Platform: UNKNOWN
